kubebuild/__init__.py
kubebuild/app.py
kubebuild/constant/__init__.py
kubebuild/constant/resource_names.py
kubebuild/error/__init__.py
kubebuild/error/validation.py
kubebuild/resource/__init__.py
kubebuild/resource/configmap.py
kubebuild/resource/deployment.py
kubebuild/resource/ingress.py
kubebuild/resource/namespace.py
kubebuild/resource/pvc.py
kubebuild/resource/secret.py
kubebuild/resource/service.py
kubebuild/resource/volume.py
kubebuild-1.1.0.dist-info/METADATA
kubebuild-1.1.0.dist-info/WHEEL
kubebuild-1.1.0.dist-info/entry_points.txt
kubebuild-1.1.0.dist-info/top_level.txt
kubebuild-1.1.0.dist-info/RECORD
