Metadata-Version: 2.1
Name: kubebuild
Version: 1.1.0
Summary: Kubebuild - Kubernetes YAML Generator and Deployment Tool
Home-page: https://github.com/ahmedkmadani/kubebuild.git
Author: Ahmed K. Madani
Author-email: ahmedk.madani@outlook.com
Classifier: Programming Language :: Python :: 3
Classifier: License :: OSI Approved :: MIT License
Classifier: Operating System :: OS Independent
Requires-Python: >=3.6
Requires-Dist: typer
Requires-Dist: PyInquirer
Requires-Dist: PyYAML
Requires-Dist: rich
